{
    "apps" : [
        {
            "name" : "executor",
            "cwd" : ".",
            "script" : "npm run executor",
            "watch" : false,
            "autorestart" : true,
            "args": [ "--color"]
        },
        {
            "name" : "output",
            "cwd" : ".",
            "script" : "npm run output",
            "watch" : false,
            "autorestart" : true,
            "restart_delay" : 10000
        },
        {
            "name" : "batch",
            "cwd" : ".",
            "script" : "npm run batch",
            "watch" : false,
            "autorestart" : true
        },
        {
            "name" : "challenger",
            "cwd" : ".",
            "script" : "npm run challenger",
            "watch" : false,
            "autorestart" : true
        }
    ]
}